SEM
