Metadata-Version: 1.0
Name: django-sem
Version: 0.2.2
Summary: Useful tool for sending signed emails.
Home-page: http://pypi.python.org/pypi/SignedEmailMessage/
Author: Jakub Wasielak
Author-email: kuba.wasielak@gmail.com
License: LICENSE.txt
Platform: UNKNOWN
